Metadata-Version: 1.1
Name: rtrpy3
Version: 0.2.5
Summary: Contentful Rich Text Renderer
Home-page: https://github.com/contentful/rich-text-renderer.py
Author: Contentful GmbH (David Litvak Bruno)
Author-email: david.litvak@contentful.com
License: MIT
Keywords: contentful delivery cda cms content
Platform: UNKNOWN
Classifier: Development Status :: 5 - Production/Stable
Classifier: Topic :: Software Development :: Libraries
Classifier: Intended Audience :: Developers
Classifier: License :: OSI Approved :: MIT License
Classifier: Natural Language :: English
Classifier: Programming Language :: Python :: 2
Classifier: Programming Language :: Python :: 2.7
Classifier: Programming Language :: Python :: 3
Classifier: Programming Language :: Python :: 3.1
Classifier: Programming Language :: Python :: 3.2
Classifier: Programming Language :: Python :: 3.3
Classifier: Programming Language :: Python :: 3.4
Classifier: Programming Language :: Python :: 3.5
Classifier: Programming Language :: Python :: 3.6
